{
  "HALProvider": {
    "Other Devices": {
      "Talon FX[0]/Integrated Sensor": {
        "header": {
          "open": true
        }
      },
      "Talon FX[1]/Integrated Sensor": {
        "header": {
          "open": true
        }
      },
      "Talon FX[2]": {
        "header": {
          "open": true
        }
      },
      "Talon FX[2]/Integrated Sensor": {
        "header": {
          "open": true
        }
      },
      "Talon FX[3]/Integrated Sensor": {
        "header": {
          "open": true
        }
      }
    }
  },
  "NTProvider": {
    "types": {
      "/FMSInfo": "FMSInfo",
      "/LiveWindow/DriveTrain": "Subsystem",
      "/LiveWindow/Ungrouped/ADXRS450_Gyro[0]": "Gyro",
      "/LiveWindow/Ungrouped/DifferentialDrive[1]": "DifferentialDrive",
      "/LiveWindow/Ungrouped/PIDController[1]": "PIDController",
      "/LiveWindow/Ungrouped/PIDController[2]": "PIDController",
      "/LiveWindow/Ungrouped/Scheduler": "Scheduler",
      "/LiveWindow/Ungrouped/Talon FX [1]": "Motor Controller",
      "/LiveWindow/Ungrouped/Talon FX [3]": "Motor Controller"
    }
  }
}
